{"@odata.context":"/redfish/v1/$metadata#PCIeFunction.PCIeFunction","@odata.etag":"1559839258","@odata.id":"/redfish/v1/Systems/System.Embedded.1/PCIeFunction/25-0-2","@odata.type":"#PCIeFunction.v1_1_1.PCIeFunction","ClassCode":"0x000002","Description":"BCM57800 1-Gigabit Ethernet","DeviceClass":"NetworkController","DeviceId":"0x168a","FunctionId":2,"FunctionType":"Physical","Id":"25-0-2","Links":{"Drives":[],"Drives@odata.count":0,"EthernetInterfaces":[{"@odata.id":"/redfish/v1/Systems/System.Embedded.1/EthernetInterfaces/NIC.Integrated.1-3-1"}],"EthernetInterfaces@odata.count":1,"PCIeDevice":{"@odata.id":"/redfish/v1/Systems/System.Embedded.1/PCIeDevice/25-0"},"StorageControllers":[],"StorageControllers@odata.count":0},"Name":"BCM57800 1-Gigabit Ethernet","Oem":{"Dell":{"DellPCIeFunction":{"@odata.context":"/redfish/v1/$metadata#DellPCIeFunction.DellPCIeFunction","@odata.id":"/redfish/v1/Dell/Systems/System.Emdedded.1/DellPCIeFunction/NIC.Integrated.1-3-1","@odata.type":"#DellPCIeFunction.v1_0_0.DellPCIeFunction","DataBusWidth":"Unknown","Description":"BCM57800 1-Gigabit Ethernet","SlotType":"Unknown"}}},"RevisionId":"0x10","Status":{"Health":"OK","HealthRollup":"OK","State":"Enabled"},"SubsystemId":"0x1f67","SubsystemVendorId":"0x1028","VendorId":"0x14e4"}