{
  "@odata.context": "/redfish/v1/$metadata#LogEntry.LogEntry",
  "@odata.id": "/redfish/v1/Managers/iDRAC.Embedded.1/LogServices/Lclog/Entries/1825",
  "@odata.type": "#LogEntry.v1_4_0.LogEntry",
  "Created": "2020-05-25T13:29:49-05:00",
  "Description": " Log Entry 1825",
  "EntryType": "Oem",
  "Id": "1825",
  "Links": {},
  "Message": "The process of installing an operating system or hypervisor is successfully completed.",
  "MessageId": "OSD063",
  "Name": " Log Entry 1825",
  "OemRecordFormat": "Dell",
  "Severity": "OK"
}
