{"@odata.context":"/redfish/v1/$metadata#DellPresenceAndStatusSensor.DellPresenceAndStatusSensor","@odata.id":"/redfish/v1/Dell/Systems/System.Embedded.1/DellPresenceAndStatusSensor/iDRAC.Embedded.1%23IDSDMSD2","@odata.type":"#DellPresenceAndStatusSensor.v1_0_0.DellPresenceAndStatusSensor","CurrentState":"Present","Description":"An instance of DellPresenceAndStatusSensor will have presence and status sensor specific data.","DeviceID":"iDRAC.Embedded.1#IDSDMSD2","ElementName":"IDSDM SD2","Id":"iDRAC.Embedded.1#IDSDMSD2","Name":"DellPresenceAndStatusSensor","SensorType":"Other"}